{
    "country": "Bolivia",
    "infobox": {
        "Area": {
            "Total (km2)": 1098581.0,
            "Water (%)": 1.29
        },
        "Economy": {
            "Currency": [
                "Boliviano"
            ],
            "GDP ( PPP )": {
                "Per capita ($)": 11574.0,
                "Total ($)": 144098000000.0
            },
            "GDP (nominal)": {
                "Per capita ($)": 4525.0,
                "Total ($)": 56339000000.0
            },
            "Gini": 40.9,
            "HDI": 0.733
        },
        "General": {
            "Ethnic groups": {
                "Unknown": 100.0
            },
            "Primary Language": [
                "Aymara",
                "Guarani",
                "Quechua",
                "Spanish"
            ],
            "Religion": {
                "Christianity": {
                    "breakdown": {
                        "Catholicism (%)": 81.4,
                        "other Christian (%)": 11.4
                    },
                    "percentage": 92.8
                },
                "no religion (%)": 6.5,
                "other (%)": 0.7
            }
        },
        "Government": {
            "Government": "Unitary presidential republic"
        },
        "Population": {
            "Count": 11365333.0,
            "Density (/km2)": 10.4
        }
    }
}