{
    "country": "Czech Republic",
    "infobox": {
        "Area": {
            "Total (km2)": 78871.0,
            "Water (%)": 2.16
        },
        "Economy": {
            "Currency": [
                "Czech koruna"
            ],
            "GDP ( PPP )": {
                "Per capita ($)": 56686.0,
                "Total ($)": 619881000000.0
            },
            "GDP (nominal)": {
                "Per capita ($)": 31365.0,
                "Total ($)": 342992000000.0
            },
            "Gini": 24.4,
            "HDI": 0.915
        },
        "General": {
            "Ethnic groups": {
                "Czechs (%)": 89,
                "Moravians (%)": 3.3,
                "Slovaks (%)": 0.9,
                "Ukrainians (%)": 0.7,
                "other (%)": 2.1,
                "two nationalities (%)": 4
            },
            "Primary Language": [
                "Czech"
            ],
            "Religion": {
                "Christianity": {
                    "breakdown": {
                        "Catholicism (%)": 9.3,
                        "other Christian (%)": 2.4
                    },
                    "percentage": 11.7
                },
                "no religion (%)": 56.9,
                "other (%)": 1.2,
                "unanswered (%)": 30.1
            }
        },
        "Government": {
            "Government": "Unitary parliamentary republic"
        },
        "Population": {
            "Count": 10900555.0,
            "Density (/km2)": 133.0
        }
    }
}