{
    "country": "Kuwait",
    "infobox": {
        "Area": {
            "Total": 17818.0,
            "Water": 0.0
        },
        "Economy": {
            "Currency": [
                "Kuwaiti dinar"
            ],
            "GDP ( PPP )": {
                "Per capita": 50960.0,
                "Total": 260500000000.0
            },
            "GDP (nominal)": {
                "Per capita": 29950.0,
                "Total": 153100000000.0
            },
            "Gini": null,
            "HDI": 0.852
        },
        "General": {
            "Ethnic groups": {
                "African": 1.0,
                "Arab": 57.8,
                "Other": 0.9,
                "South Asian": 40.3
            },
            "Primary Language": [
                "Arabic"
            ],
            "Religion": {
                "Christianity": 18.2,
                "Islam": 74.6,
                "Other": 7.2
            }
        },
        "Government": {
            "Government": "Unitary semi-constitutional monarchy",
            "Legislature": "Parliament"
        },
        "Population": {
            "Count": 4985716.0,
            "Density": 200.2
        }
    }
}