{
    "country": "Paraguay",
    "infobox": {
        "General": {
            "Official Language": "Spanish Guarani",
            "Religion": {
                "Christianity": {
                    "percentage": 95.5,
                    "breakdown": {
                        "Catholicism (%)": 87.4,
                        "other Christian (%)": 8.1
                    }
                },
                "no religion (%)": 4.1,
                "other (%)": 0.4
            },
            "Ethnic groups": {
                "Mestizo (%)": 95,
                "White (%)": 5
            }
        },
        "Government": {
            "Government": "Unitary presidential republic"
        },
        "Area": {
            "Total (km2)": 406752,
            "Water (%)": 2.6
        },
        "Population": {
            "Count": 6413627,
            "Density": "39/sq mi"
        },
        "Economy": {
            "GDP ( PPP )": {
                "Total ($)": 145110000000,
                "Per capita ($)": 22462
            },
            "GDP (nominal)": {
                "Total ($)": 51670000000,
                "Per capita ($)": 7990
            },
            "Gini": 44.4,
            "HDI": 0.756,
            "Currency": "Guaraní"
        }
    }
}