{
  "country": "Dominican Republic",
  "infobox": {
    "General": {
      "Capital": "Santo Domingo",
      "Official languages": "Spanish",
      "Ethnic groups": {
        "Mixed": "71.72%",
        "White": "18.7%",
        "Black": "7.45%",
        "East Asian": "0.33%",
        "other": "0.37%",
        "no answer": "1.43%"
      },
      "Religion": {
        "Christianity": "74.6%",
        "Catholicism": "52.5%",
        "Protestantism": "21%",
        "other Christian": "1.1%",
        "no religion": "22%",
        "other": "1.4%",
        "unspecified": "2%"
      },
      "Demonyms": "Dominican Quisqueyan (colloquial)"
    },
    "Government": {
      "Government": "Unitary presidential republic",
      "Legislature": "Congress",
      "Upper house": "Senate",
      "Lower house": "Chamber of Deputies"
    },
    "Area": {
      "Total": "48,671 km 2 (18,792 sq mi) ( 128th )",
      "Water (%": "0.7"
    },
    "Population": {
      "2025 estimate": "11,532,151 ( 88th )",
      "Density": "220/km 2 (569.8/sq mi) ( 64th )"
    },
    "Economy": {
      "GDP ( PPP": {
        "Details": "2025 estimate",
        "Total": "$334.292 billion ( 64th )",
        "Per capita": "$30,710 ( 67th )"
      },
      "GDP (nominal": {
        "Details": "2025 estimate",
        "Total": "$135.545 billion ( 64th )",
        "Per capita": "$12,452 ( 74th )"
      },
      "Gini": "39 medium inequality",
      "HDI": "0.776 high ( 89th )",
      "Currency": "Dominican peso ( DOP )"
    }
  }
}