{
  "country": "Ecuador",
  "infobox": {
    "General": {
      "Capital": "Quito",
      "Largest city": "Guayaquil",
      "Official languages": "Spanish",
      "Ethnic groups": {
        "Mestizo (mixed White & Indigenous": "77.47%",
        "Montubio (coastal Mestizo": "7.7%",
        "Indigenous": "7.69%",
        "Black": "4.81%",
        "White": "2.21%",
        "other": "0.12%"
      },
      "Religion": {
        "Christianity": "89.3%",
        "Catholic": "68.2%",
        "Evangelical": "18%",
        "other": "2%",
        "no religion": "8.9%"
      },
      "Demonyms": "Ecuadorian"
    },
    "Government": {
      "Government": "Unitary presidential republic",
      "Legislature": "National Assembly"
    },
    "Area": {
      "Total": "283,561 km 2 (109,484 sq mi) ( 73rd )",
      "Excluding the Galapagos Islands": "276,841 km 2 (106,889 sq mi)"
    },
    "Population": {
      "2023 estimate": "17,483,326",
      "2022 census": "16,938,986 ( 73rd )",
      "Density": "69/km 2 (178.7/sq mi) ( 148th )"
    },
    "Economy": {
      "GDP ( PPP": {
        "Details": "2025 estimate",
        "Total": "$304.230 billion ( 66th )",
        "Per capita": "$16,180 ( 109th )"
      },
      "GDP (nominal": {
        "Details": "2025 estimate",
        "Total": "$130.530 billion ( 63rd )",
        "Per capita": "$7,210 ( 95th )"
      },
      "Gini": "45.2 medium inequality",
      "HDI": "0.777 high ( 88th )",
      "Currency": "United States dollar a ( USD )"
    }
  }
}