<?xml version="1.0" encoding="utf-8"?>
<countries>
  <country>Estonia</country>
  <iso3>EST</iso3>
  <demographics>
    <total_population>
      <value>1372341</value>
      <year>2024</year>
    </total_population>
    <population_density_per_sq_km>
      <value>32.0684764802247</value>
      <year>2023</year>
    </population_density_per_sq_km>
    <population_growth_rate_percent>
      <value>0.149856351926424</value>
      <year>2024</year>
    </population_growth_rate_percent>
    <urban_population_percent>
      <value>70.6981161541961</value>
      <year>2024</year>
    </urban_population_percent>
    <rural_population_percent>
      <value>29.3018838458039</value>
      <year>2024</year>
    </rural_population_percent>
    <age_dependency_ratio_percent>
      <value>58.5663479181206</value>
      <year>2024</year>
    </age_dependency_ratio_percent>
    <net_migration>
      <value>-13350</value>
      <year>2025</year>
    </net_migration>
  </demographics>
  <economy>
    <gdp_current_usd>
      <value>43130419829.35</value>
      <year>2024</year>
    </gdp_current_usd>
    <gdp_per_capita_ppp>
      <value>49968.7108278373</value>
      <year>2024</year>
    </gdp_per_capita_ppp>
    <gdp_per_capita_current_usd>
      <value>31428.3547816104</value>
      <year>2024</year>
    </gdp_per_capita_current_usd>
    <gdp_growth_rate_percent>
      <value>-0.0900428648493801</value>
      <year>2024</year>
    </gdp_growth_rate_percent>
    <unemployment_percent>
      <value>8.313</value>
      <year>2025</year>
    </unemployment_percent>
    <inflation_percent>
      <value>3.52056053296586</value>
      <year>2024</year>
    </inflation_percent>
    <agriculture_value_added_percent_gdp>
      <value>1.76684782957851</value>
      <year>2024</year>
    </agriculture_value_added_percent_gdp>
    <agricultural_land_percent>
      <value>23.1219283875497</value>
      <year>2023</year>
    </agricultural_land_percent>
    <industry_value_added_percent_gdp>
      <value>20.148164473251</value>
      <year>2024</year>
    </industry_value_added_percent_gdp>
    <services_value_added_percent_gdp>
      <value>65.6971144966199</value>
      <year>2024</year>
    </services_value_added_percent_gdp>
    <domestic_credit_private_sector_percent_gdp>
      <value>60.5354220304166</value>
      <year>2024</year>
    </domestic_credit_private_sector_percent_gdp>
    <poverty_headcount_ratio_percent>
      <value>0.3</value>
      <year>2023</year>
    </poverty_headcount_ratio_percent>
    <gini_index>
      <value>30.7</value>
      <year>2023</year>
    </gini_index>
    <income_share_lowest_20_percent>
      <value>8.3</value>
      <year>2023</year>
    </income_share_lowest_20_percent>
  </economy>
  <trade>
    <trade_percent_gdp>
      <value>151.037702410455</value>
      <year>2024</year>
    </trade_percent_gdp>
    <exports_percent_gdp>
      <value>75.6694833213142</value>
      <year>2024</year>
    </exports_percent_gdp>
    <imports_percent_gdp>
      <value>75.3682190891409</value>
      <year>2024</year>
    </imports_percent_gdp>
    <trade_balance_percent_gdp>
      <value>0.301264232173345</value>
      <year>2024</year>
    </trade_balance_percent_gdp>
    <fdi_net_inflows_percent_gdp>
      <value>-7.97097840452121</value>
      <year>2024</year>
    </fdi_net_inflows_percent_gdp>
    <food_imports_percent_of_merchandise>
      <value>14.2452823132285</value>
      <year>2024</year>
    </food_imports_percent_of_merchandise>
  </trade>
  <debt>
    <central_government_debt_percent_gdp>
      <value/>
      <year/>
    </central_government_debt_percent_gdp>
    <external_debt_percent_gni>
      <value/>
      <year/>
    </external_debt_percent_gni>
    <debt_service_percent_exports>
      <value/>
      <year/>
    </debt_service_percent_exports>
  </debt>
  <education>
    <literacy_rate_percent>
      <value/>
      <year/>
    </literacy_rate_percent>
    <primary_school_enrollment_gross>
      <value>98.3381576538086</value>
      <year>2023</year>
    </primary_school_enrollment_gross>
    <secondary_school_enrollment_gross>
      <value>108.442070007324</value>
      <year>2023</year>
    </secondary_school_enrollment_gross>
    <tertiary_school_enrollment_gross>
      <value>67.6179275512695</value>
      <year>2023</year>
    </tertiary_school_enrollment_gross>
    <education_expenditure_percent_gdp>
      <value>5.20733976364136</value>
      <year>2022</year>
    </education_expenditure_percent_gdp>
  </education>
  <health>
    <life_expectancy_years>
      <value>78.490243902439</value>
      <year>2023</year>
    </life_expectancy_years>
    <infant_mortality_per_1000>
      <value>1.6</value>
      <year>2023</year>
    </infant_mortality_per_1000>
    <under_5_mortality_per_1000>
      <value>2.1</value>
      <year>2023</year>
    </under_5_mortality_per_1000>
    <current_health_expenditure_percent_gdp>
      <value>7.83648062</value>
      <year>2024</year>
    </current_health_expenditure_percent_gdp>
    <physicians_per_1000_people>
      <value>3.469</value>
      <year>2022</year>
    </physicians_per_1000_people>
    <undernourishment_prevalence_percent>
      <value>2.5</value>
      <year>2023</year>
    </undernourishment_prevalence_percent>
  </health>
  <infrastructure>
    <access_to_electricity_percent>
      <value>100</value>
      <year>2023</year>
    </access_to_electricity_percent>
    <basic_drinking_water_percent>
      <value>99.9999970212441</value>
      <year>2024</year>
    </basic_drinking_water_percent>
    <basic_sanitation_percent>
      <value>99.0214935273124</value>
      <year>2024</year>
    </basic_sanitation_percent>
    <internet_users_percent>
      <value>92.238</value>
      <year>2024</year>
    </internet_users_percent>
    <fixed_broadband_subscriptions_per_100>
      <value>35.254</value>
      <year>2023</year>
    </fixed_broadband_subscriptions_per_100>
    <mobile_subscriptions_per_100>
      <value>150.196</value>
      <year>2023</year>
    </mobile_subscriptions_per_100>
    <transport_infrastructure_quality_lpi>
      <value>3.5</value>
      <year>2022</year>
    </transport_infrastructure_quality_lpi>
  </infrastructure>
  <energy_and_environment>
    <renewable_energy_percent>
      <value>38</value>
      <year>2021</year>
    </renewable_energy_percent>
    <energy_use_per_capita_kg_oil_eq>
      <value>3089.39333905852</value>
      <year>2023</year>
    </energy_use_per_capita_kg_oil_eq>
    <forest_area_percent_land>
      <value>57.0652937046572</value>
      <year>2023</year>
    </forest_area_percent_land>
    <electricity_from_fossil_fuels_percent>
      <value>49.5909486510009</value>
      <year>2023</year>
    </electricity_from_fossil_fuels_percent>
    <electricity_from_hydroelectric_percent>
      <value>0.4177545691906</value>
      <year>2023</year>
    </electricity_from_hydroelectric_percent>
    <electricity_from_nuclear_percent>
      <value>0</value>
      <year>2021</year>
    </electricity_from_nuclear_percent>
    <electricity_from_renewables_excl_hydro_percent>
      <value>39.638117712382</value>
      <year>2021</year>
    </electricity_from_renewables_excl_hydro_percent>
    <energy_imports_percent_of_use>
      <value>3.77111519842947</value>
      <year>2023</year>
    </energy_imports_percent_of_use>
  </energy_and_environment>
  <governance>
    <government_effectiveness>
      <value>1.2634699344635</value>
      <year>2023</year>
    </government_effectiveness>
    <rule_of_law>
      <value>1.42638897895813</value>
      <year>2023</year>
    </rule_of_law>
    <control_of_corruption>
      <value>1.53812229633331</value>
      <year>2023</year>
    </control_of_corruption>
    <political_stability>
      <value>0.660533905029297</value>
      <year>2023</year>
    </political_stability>
    <regulatory_quality>
      <value>1.42964351177216</value>
      <year>2023</year>
    </regulatory_quality>
  </governance>
  <security>
    <intentional_homicides_per_100k>
      <value>1.53599045052794</value>
      <year>2023</year>
    </intentional_homicides_per_100k>
    <battle_related_deaths>
      <value/>
      <year/>
    </battle_related_deaths>
  </security>
  <world_bank_country_name>
    <item>Estonia</item>
  </world_bank_country_name>
</countries>
