<?xml version="1.0" encoding="utf-8"?>
<countries>
  <country>Mozambique</country>
  <iso3>MOZ</iso3>
  <demographics>
    <total_population>
      <value>34631766</value>
      <year>2024</year>
    </total_population>
    <population_density_per_sq_km>
      <value>42.7721457819375</value>
      <year>2023</year>
    </population_density_per_sq_km>
    <population_growth_rate_percent>
      <value>2.91994049442347</value>
      <year>2024</year>
    </population_growth_rate_percent>
    <urban_population_percent>
      <value>36.4332337447237</value>
      <year>2024</year>
    </urban_population_percent>
    <rural_population_percent>
      <value>63.5667662552763</value>
      <year>2024</year>
    </rural_population_percent>
    <age_dependency_ratio_percent>
      <value>89.5117827853714</value>
      <year>2024</year>
    </age_dependency_ratio_percent>
    <net_migration>
      <value>-65573</value>
      <year>2025</year>
    </net_migration>
  </demographics>
  <economy>
    <gdp_current_usd>
      <value>22745341305.0622</value>
      <year>2024</year>
    </gdp_current_usd>
    <gdp_per_capita_ppp>
      <value>1705.37919520416</value>
      <year>2024</year>
    </gdp_per_capita_ppp>
    <gdp_per_capita_current_usd>
      <value>656.776824637306</value>
      <year>2024</year>
    </gdp_per_capita_current_usd>
    <gdp_growth_rate_percent>
      <value>2.14854964610538</value>
      <year>2024</year>
    </gdp_growth_rate_percent>
    <unemployment_percent>
      <value>6.628</value>
      <year>2025</year>
    </unemployment_percent>
    <inflation_percent>
      <value>4.07856834812022</value>
      <year>2024</year>
    </inflation_percent>
    <agriculture_value_added_percent_gdp>
      <value>25.1764811733064</value>
      <year>2024</year>
    </agriculture_value_added_percent_gdp>
    <agricultural_land_percent>
      <value>52.7891502835779</value>
      <year>2023</year>
    </agricultural_land_percent>
    <industry_value_added_percent_gdp>
      <value>21.9003012294797</value>
      <year>2024</year>
    </industry_value_added_percent_gdp>
    <services_value_added_percent_gdp>
      <value>41.0964463998045</value>
      <year>2024</year>
    </services_value_added_percent_gdp>
    <domestic_credit_private_sector_percent_gdp>
      <value>17.5995711148942</value>
      <year>2024</year>
    </domestic_credit_private_sector_percent_gdp>
    <poverty_headcount_ratio_percent>
      <value>81.4</value>
      <year>2022</year>
    </poverty_headcount_ratio_percent>
    <gini_index>
      <value>49.6</value>
      <year>2022</year>
    </gini_index>
    <income_share_lowest_20_percent>
      <value>4.7</value>
      <year>2022</year>
    </income_share_lowest_20_percent>
  </economy>
  <trade>
    <trade_percent_gdp>
      <value>95.659420351194</value>
      <year>2024</year>
    </trade_percent_gdp>
    <exports_percent_gdp>
      <value>42.8352957458</value>
      <year>2024</year>
    </exports_percent_gdp>
    <imports_percent_gdp>
      <value>52.8241246053941</value>
      <year>2024</year>
    </imports_percent_gdp>
    <trade_balance_percent_gdp>
      <value>-9.98882885959411</value>
      <year>2024</year>
    </trade_balance_percent_gdp>
    <fdi_net_inflows_percent_gdp>
      <value>15.4256916399298</value>
      <year>2024</year>
    </fdi_net_inflows_percent_gdp>
    <food_imports_percent_of_merchandise>
      <value>19.5889066152119</value>
      <year>2024</year>
    </food_imports_percent_of_merchandise>
  </trade>
  <debt>
    <central_government_debt_percent_gdp>
      <value>71.7932488373315</value>
      <year>2024</year>
    </central_government_debt_percent_gdp>
    <external_debt_percent_gni>
      <value>350.573066715697</value>
      <year>2024</year>
    </external_debt_percent_gni>
    <debt_service_percent_exports>
      <value>46.5096494923949</value>
      <year>2024</year>
    </debt_service_percent_exports>
  </debt>
  <education>
    <literacy_rate_percent>
      <value>61.6778205151772</value>
      <year>2022</year>
    </literacy_rate_percent>
    <primary_school_enrollment_gross>
      <value>119.162225223393</value>
      <year>2022</year>
    </primary_school_enrollment_gross>
    <secondary_school_enrollment_gross>
      <value>37.2411918640137</value>
      <year>2017</year>
    </secondary_school_enrollment_gross>
    <tertiary_school_enrollment_gross>
      <value>7.4630510423433</value>
      <year>2018</year>
    </tertiary_school_enrollment_gross>
    <education_expenditure_percent_gdp>
      <value>5.97607342054314</value>
      <year>2022</year>
    </education_expenditure_percent_gdp>
  </education>
  <health>
    <life_expectancy_years>
      <value>63.611</value>
      <year>2023</year>
    </life_expectancy_years>
    <infant_mortality_per_1000>
      <value>45.4</value>
      <year>2023</year>
    </infant_mortality_per_1000>
    <under_5_mortality_per_1000>
      <value>61.7</value>
      <year>2023</year>
    </under_5_mortality_per_1000>
    <current_health_expenditure_percent_gdp>
      <value>8.50126553</value>
      <year>2023</year>
    </current_health_expenditure_percent_gdp>
    <physicians_per_1000_people>
      <value>0.175</value>
      <year>2022</year>
    </physicians_per_1000_people>
    <undernourishment_prevalence_percent>
      <value>21.8</value>
      <year>2023</year>
    </undernourishment_prevalence_percent>
  </health>
  <infrastructure>
    <access_to_electricity_percent>
      <value>36</value>
      <year>2023</year>
    </access_to_electricity_percent>
    <basic_drinking_water_percent>
      <value>66.6252441342671</value>
      <year>2024</year>
    </basic_drinking_water_percent>
    <basic_sanitation_percent>
      <value>38.5900804802051</value>
      <year>2024</year>
    </basic_sanitation_percent>
    <internet_users_percent>
      <value>19.8434</value>
      <year>2023</year>
    </internet_users_percent>
    <fixed_broadband_subscriptions_per_100>
      <value>0.197785</value>
      <year>2022</year>
    </fixed_broadband_subscriptions_per_100>
    <mobile_subscriptions_per_100>
      <value>45.8178</value>
      <year>2022</year>
    </mobile_subscriptions_per_100>
    <transport_infrastructure_quality_lpi>
      <value>2.238017</value>
      <year>2016</year>
    </transport_infrastructure_quality_lpi>
  </infrastructure>
  <energy_and_environment>
    <renewable_energy_percent>
      <value>76.9</value>
      <year>2021</year>
    </renewable_energy_percent>
    <energy_use_per_capita_kg_oil_eq>
      <value>358.637694361749</value>
      <year>2022</year>
    </energy_use_per_capita_kg_oil_eq>
    <forest_area_percent_land>
      <value>45.8130349195046</value>
      <year>2023</year>
    </forest_area_percent_land>
    <electricity_from_fossil_fuels_percent>
      <value>16.295122200634</value>
      <year>2022</year>
    </electricity_from_fossil_fuels_percent>
    <electricity_from_hydroelectric_percent>
      <value>82.6925043460477</value>
      <year>2022</year>
    </electricity_from_hydroelectric_percent>
    <electricity_from_nuclear_percent>
      <value>0</value>
      <year>2021</year>
    </electricity_from_nuclear_percent>
    <electricity_from_renewables_excl_hydro_percent>
      <value>0.721518316280549</value>
      <year>2021</year>
    </electricity_from_renewables_excl_hydro_percent>
    <energy_imports_percent_of_use>
      <value>-106.352427255745</value>
      <year>2022</year>
    </energy_imports_percent_of_use>
  </energy_and_environment>
  <governance>
    <government_effectiveness>
      <value>-0.716628909111023</value>
      <year>2023</year>
    </government_effectiveness>
    <rule_of_law>
      <value>-1.02632343769073</value>
      <year>2023</year>
    </rule_of_law>
    <control_of_corruption>
      <value>-0.828437745571136</value>
      <year>2023</year>
    </control_of_corruption>
    <political_stability>
      <value>-1.26869130134583</value>
      <year>2023</year>
    </political_stability>
    <regulatory_quality>
      <value>-0.708528399467468</value>
      <year>2023</year>
    </regulatory_quality>
  </governance>
  <security>
    <intentional_homicides_per_100k>
      <value/>
      <year/>
    </intentional_homicides_per_100k>
    <battle_related_deaths>
      <value>151</value>
      <year>2024</year>
    </battle_related_deaths>
  </security>
  <world_bank_country_name>
    <item>Mozambique</item>
  </world_bank_country_name>
</countries>
